ctags_ue4cli/__init__.py
ctags_ue4cli/descriptor.py
ctags_ue4cli/main.py
ctags_ue4cli/commands/__init__.py
ctags_ue4cli/commands/ctags.py
ctags_ue4cli-0.0.4.dist-info/LICENSE
ctags_ue4cli-0.0.4.dist-info/METADATA
ctags_ue4cli-0.0.4.dist-info/WHEEL
ctags_ue4cli-0.0.4.dist-info/entry_points.txt
ctags_ue4cli-0.0.4.dist-info/top_level.txt
ctags_ue4cli-0.0.4.dist-info/RECORD
