Metadata-Version: 2.1
Name: ctags-ue4cli
Version: 0.0.4
Summary: ctags plugin for ue4cli
Home-page: http://github.com/drichardson/ctags-ue4cli
Author: Doug Richardson
Author-email: doug@rekt.email
License: UNKNOWN
Keywords: epic unreal engine ctags
Platform: UNKNOWN
Classifier: License :: OSI Approved :: The Unlicense (Unlicense)
Classifier: Programming Language :: Python :: 3.8
Classifier: Topic :: Software Development :: Build Tools
Classifier: Environment :: Console
Requires-Python: >=3.7
Requires-Dist: ue4cli (>=0.0.51)
